asif/__init__.py
asif/bot.py
asif/command_codes.py
asif/commands.py
asif/util.py
asif-0.3.2.dist-info/LICENSE
asif-0.3.2.dist-info/METADATA
asif-0.3.2.dist-info/WHEEL
asif-0.3.2.dist-info/top_level.txt
asif-0.3.2.dist-info/RECORD
