Metadata-Version: 2.1
Name: asif
Version: 0.3.2
Summary: A Python 3.6+, asyncio- and decorator-based IRC framework
Home-page: http://github.com/minus7/asif
Author: minus
Author-email: minus@mnus.de
License: MIT
Keywords: irc bot framework
Platform: UNKNOWN
Classifier: Development Status :: 3 - Alpha
Classifier: Intended Audience :: Developers
Classifier: License :: OSI Approved :: MIT License
Classifier: Programming Language :: Python :: 3.6
License-File: LICENSE
